LICENSE
README.md
setup.cfg
setup.py
jsonLookup/__init__.py
jsonLookup/has_lookup.py
jsonLookup/jcontains_lookup.py
jsonLookup/jlength_lookup.py
jsonLookup/shas_lookup.py
jsonLookup.egg-info/PKG-INFO
jsonLookup.egg-info/SOURCES.txt
jsonLookup.egg-info/dependency_links.txt
jsonLookup.egg-info/top_level.txt