Metadata-Version: 2.1
Name: jsonLookup
Version: 0.8.0
Summary: Search MySQL JSON fields in Django
Home-page: https://github.com/mkalioby/jsonLookup
Author: Mohamed El-Kalioby
Author-email: mkalioby@mkalioby.com
License: UNKNOWN
Keywords: django,django,mysql
Platform: UNKNOWN
